nonsql/__init__.py
nonsql/cli.py
nonsql/database.py
nonsql-1.1.2.dist-info/METADATA
nonsql-1.1.2.dist-info/WHEEL
nonsql-1.1.2.dist-info/entry_points.txt
nonsql-1.1.2.dist-info/top_level.txt
nonsql-1.1.2.dist-info/RECORD
