Metadata-Version: 2.2
Name: nonsql
Version: 1.1.2
Summary: A NoSQL database management tool
Home-page: https://github.com/ishanoshada/nonsql
Author: Ishan Osahda
Author-email: ishan.kodithuwakku.offical@gmail.com
Classifier: Programming Language :: Python :: 3
Classifier: License :: OSI Approved :: MIT License
Classifier: Operating System :: OS Independent
Requires-Dist: click>=7.0
Requires-Dist: pyyaml>=5.4.0
Dynamic: author
Dynamic: author-email
Dynamic: classifier
Dynamic: description
Dynamic: description-content-type
Dynamic: home-page
Dynamic: requires-dist
Dynamic: summary
